Metadata-Version: 1.0
Name: imphook
Version: 0.5.1
Summary: Simple and clear import hooks for Python - import anything as if it were a Python module
Home-page: https://github.com/pfalcon/python-imphook
Author: Paul Sokolovsky
Author-email: pfalcon@users.sourceforge.net
License: MIT
Platform: UNKNOWN
